typex/__init__.py
typex/basic.py
typex/constants.py
typex/decorators.py
typex/dirstruct.py
typex-0.3.3.dist-info/LICENSE
typex-0.3.3.dist-info/METADATA
typex-0.3.3.dist-info/WHEEL
typex-0.3.3.dist-info/top_level.txt
typex-0.3.3.dist-info/RECORD
