Metadata-Version: 2.1
Name: typex
Version: 0.3.3
Summary: Python fundamental type extension.
Home-page: https://github.com/numlinka/pytypex
Author: numlinka
Author-email: numlinka@163.com
License: MIT
Keywords: type,class,static,singleton,multiton,atomic
Classifier: License :: OSI Approved :: MIT License
Classifier: Programming Language :: Python :: 3
Requires-Python: >=3.8
License-File: LICENSE
